RobotmkLibrary/__init__.py
robotframework_robotmklibrary-0.0.4.dist-info/METADATA
robotframework_robotmklibrary-0.0.4.dist-info/WHEEL
robotframework_robotmklibrary-0.0.4.dist-info/licenses/LICENSE
robotframework_robotmklibrary-0.0.4.dist-info/RECORD
